django_priv/__init__.py
django_priv/admin.py
django_priv/apps.py
django_priv/migrations/__init__.py
django_priv/models.py
django_priv/tests.py
django_priv/urls.py
django_priv/views.py
django_priv-0.2.0.dist-info/WHEEL
django_priv-0.2.0.dist-info/METADATA
django_priv-0.2.0.dist-info/RECORD
