Metadata-Version: 2.1
Name: django-priv
Version: 0.2.0
Summary: yow
License: MIT
Author: aprilahijriyan
Author-email: 37798612+aprilahijriyan@users.noreply.github.com
Requires-Python: >=3.8,<4.0
Classifier: License :: OSI Approved :: MIT License
Classifier: Programming Language :: Python :: 3
Classifier: Programming Language :: Python :: 3.10
Classifier: Programming Language :: Python :: 3.8
Classifier: Programming Language :: Python :: 3.9
Requires-Dist: Django (>=3.2,<4.0)
